shiftscan/__init__.py
shiftscan/cli.py
shiftscan/utils.py
shiftscan-0.1.10.dist-info/licenses/LICENSE
shiftscan-0.1.10.dist-info/METADATA
shiftscan-0.1.10.dist-info/WHEEL
shiftscan-0.1.10.dist-info/entry_points.txt
shiftscan-0.1.10.dist-info/top_level.txt
shiftscan-0.1.10.dist-info/RECORD
