Metadata-Version: 2.4
Name: shiftscan
Version: 0.1.10
Summary: ShiftScan CLI: shiftscan
Home-page: https://github.com/umutcakir/shiftscan
Author: Umut Cakir & Ali Yurtseven
Author-email: hpumut@gmail.com
Classifier: Programming Language :: Python :: 3
Classifier: License :: OSI Approved :: MIT License
Classifier: Operating System :: OS Independent
Requires-Python: >=3.6
License-File: LICENSE
Requires-Dist: biotite>=1.3.0
Requires-Dist: pandas>=2.2.3
Requires-Dist: joblib>=1.5.1
Requires-Dist: tqdm>=4.67.1
Dynamic: author
Dynamic: author-email
Dynamic: classifier
Dynamic: description
Dynamic: description-content-type
Dynamic: home-page
Dynamic: license-file
Dynamic: requires-dist
Dynamic: requires-python
Dynamic: summary
